bytehouse_mcp_server-0.1.0.dist-info/licenses/LICENSE
mcp_bytehouse/__init__.py
mcp_bytehouse/main.py
mcp_bytehouse/mcp_env.py
mcp_bytehouse/mcp_server.py
mcp_bytehouse/knowledge/cnch_merge_tree.md
mcp_bytehouse/knowledge/cnch_unique_merge_tree.md
mcp_bytehouse/knowledge/distributed.md
mcp_bytehouse/knowledge/ha_merge_tree.md
mcp_bytehouse/knowledge/ha_unique_merge_tree.md
bytehouse_mcp_server-0.1.0.dist-info/METADATA
bytehouse_mcp_server-0.1.0.dist-info/WHEEL
bytehouse_mcp_server-0.1.0.dist-info/entry_points.txt
bytehouse_mcp_server-0.1.0.dist-info/top_level.txt
bytehouse_mcp_server-0.1.0.dist-info/RECORD
