Metadata-Version: 2.4
Name: bytehouse-mcp-server
Version: 0.1.0
Summary: Add your description here
Requires-Python: >=3.13
License-File: LICENSE
Requires-Dist: mcp[cli]>=1.6.0
Requires-Dist: python-dotenv>=1.0.1
Requires-Dist: uvicorn>=0.34.0
Requires-Dist: clickhouse-connect>=0.8.0
Requires-Dist: pip-system-certs>=4.0
Dynamic: license-file
